interpals/__init__.py
interpals-0.0.1.dist-info/LICENSE
interpals-0.0.1.dist-info/METADATA
interpals-0.0.1.dist-info/WHEEL
interpals-0.0.1.dist-info/top_level.txt
interpals-0.0.1.dist-info/RECORD
