Metadata-Version: 2.1
Name: interpals
Version: 0.0.1
Summary: Interpals API wrapper to make bots easier to use
Home-page: https://github.com/forevercynical/interpals
Author: forevercynical
Author-email: me@cynical.gg
License: MIT
Keywords: interpals,interpals-bot,interpals-bots
Requires-Python: >=3.6
License-File: LICENSE
Requires-Dist: httpx
Requires-Dist: websocket-client (==1.4.1)
Requires-Dist: websockets (==10.3)
